.flake8
.gitignore
.readthedocs.yml
CHANGES.rst
CITATION.cff
LICENSE
README.rst
pyproject.toml
setup.cfg
setup.py
.devcontainer/devcontainer.json
.github/workflows/publish-to-pypi.yml
.github/workflows/python-package-with-numba.yml
.github/workflows/python-package.yml
docs/Makefile
docs/conf.py
docs/index.rst
docs/make.bat
docs/requirements.txt
docs/examples/ceers-z16-msaexp.ipynb
docs/examples/drizzled-nirspec.ipynb
docs/examples/empirical-bar-shadow.ipynb
docs/examples/lookup-table-psf.ipynb
docs/examples/process-rxj2129.ipynb
docs/examples/process-smacs0723.ipynb
docs/examples/spectral-extractions-2024.ipynb
docs/examples/spectral-pipeline-2024.ipynb
docs/examples/spectral-pipeline-2025.ipynb
docs/examples/sps-utilities.ipynb
docs/msaexp/Makefile
docs/msaexp/api.rst
docs/msaexp/install.rst
docs/msaexp/notes.rst
docs/msaexp/figures/nirspec_detector_gap_clear_prism.png
docs/msaexp/figures/nirspec_detector_gap_f070lp_g140m.png
docs/msaexp/figures/nirspec_detector_gap_f100lp_g140h.png
docs/msaexp/figures/nirspec_detector_gap_f100lp_g140m.png
docs/msaexp/figures/nirspec_detector_gap_f170lp_g235h.png
docs/msaexp/figures/nirspec_detector_gap_f170lp_g235m.png
docs/msaexp/figures/nirspec_detector_gap_f290lp_g395h.png
docs/msaexp/figures/nirspec_detector_gap_f290lp_g395m.png
msaexp/__init__.py
msaexp/drizzle.py
msaexp/ifu.py
msaexp/msa.py
msaexp/pipeline.py
msaexp/pipeline_extended.py
msaexp/pipeline_fs.py
msaexp/resample.py
msaexp/resample_numba.py
msaexp/slit_combine.py
msaexp/slit_group.py
msaexp/spectrum.py
msaexp/version.py
msaexp.egg-info/PKG-INFO
msaexp.egg-info/SOURCES.txt
msaexp.egg-info/dependency_links.txt
msaexp.egg-info/requires.txt
msaexp.egg-info/top_level.txt
msaexp/cloud/__init__.py
msaexp/cloud/combine.py
msaexp/cloud/ifu.py
msaexp/cloud/lrs.py
msaexp/cloud/redshift.py
msaexp/data/README.md
msaexp/data/fix_units.py
msaexp/data/fwhm_data.py
msaexp/data/h2_linelist.txt
msaexp/data/jwst_nirspec_g140h_disp.fits
msaexp/data/jwst_nirspec_g140m_disp.fits
msaexp/data/jwst_nirspec_g235h_disp.fits
msaexp/data/jwst_nirspec_g235m_disp.fits
msaexp/data/jwst_nirspec_g395h_disp.fits
