Metadata-Version: 2.4
Name: msaexp
Version: 0.9.14
Summary: Manual extraction of JWST NIRSpec MSA spectra directly from the telescope exposures
Home-page: https://github.com/gbrammer/msaexp
Author: G. Brammer
License: MIT
Project-URL: Source, https://github.com/gbrammer/msaexp
Project-URL: Tracker, https://github.com/gbrammer/msaexp/issues
Classifier: Development Status :: 3 - Alpha
Classifier: Intended Audience :: Science/Research
Classifier: Topic :: Scientific/Engineering :: Astronomy
Requires-Python: >=3.9
Requires-Dist: numpy
Requires-Dist: cython
Requires-Dist: matplotlib
Requires-Dist: scipy
Requires-Dist: numba
Requires-Dist: tqdm
Requires-Dist: astropy
Requires-Dist: pysiaf
Requires-Dist: jwst<1.17
Requires-Dist: crds<13.0
Requires-Dist: astroquery
Requires-Dist: grizli
Requires-Dist: eazy>=0.8.3
Requires-Dist: mastquery
Requires-Dist: astro-sedpy>=0.3.0
Requires-Dist: scikit-image
Requires-Dist: pillow<11.3
Provides-Extra: test
Requires-Dist: pytest>=5.1; extra == "test"
Requires-Dist: pytest-cov; extra == "test"
Requires-Dist: flake8; extra == "test"
Provides-Extra: docs
Requires-Dist: sphinx; extra == "docs"
Requires-Dist: sphinx-astropy; extra == "docs"
